dtags/__init__.py
dtags/commons.py
dtags/exceptions.py
dtags/files.py
dtags/style.py
dtags/version.py
dtags/commands/__init__.py
dtags/commands/activate.py
dtags/commands/d.py
dtags/commands/run.py
dtags/commands/tag.py
dtags/commands/tags.py
dtags/commands/untag.py
dtags-4.0.4.dist-info/LICENSE
dtags-4.0.4.dist-info/METADATA
dtags-4.0.4.dist-info/WHEEL
dtags-4.0.4.dist-info/entry_points.txt
dtags-4.0.4.dist-info/top_level.txt
dtags-4.0.4.dist-info/RECORD
