Metadata-Version: 2.1
Name: dtags
Version: 4.0.4
Summary: Directory Tags for Lazy Programmers
Home-page: https://github.com/joowani/dtags
Author: Joohwan Oh
Author-email: joohwan.oh@outlook.com
License: MIT
Keywords: cli,terminal
Platform: UNKNOWN
Classifier: Intended Audience :: Developers
Classifier: License :: OSI Approved :: MIT License
Classifier: Natural Language :: English
Classifier: Operating System :: MacOS
Classifier: Operating System :: Microsoft :: Windows
Classifier: Operating System :: Unix
Classifier: Programming Language :: Python :: 3
Classifier: Topic :: Utilities
Requires-Python: >=3.6
Requires-Dist: python-slugify (>=4.0.1)
Provides-Extra: dev
Requires-Dist: black ; extra == 'dev'
Requires-Dist: flake8 (>=3.8.4) ; extra == 'dev'
Requires-Dist: isort (>=5.0.0) ; extra == 'dev'
Requires-Dist: mypy (>=0.790) ; extra == 'dev'
Requires-Dist: pre-commit (>=2.9.3) ; extra == 'dev'
Requires-Dist: pytest (>=6.0.0) ; extra == 'dev'
Requires-Dist: pytest-cov (>=2.0.0) ; extra == 'dev'
